sign_vectors/__init__.py
sign_vectors/chirotopes.py
sign_vectors/functions.py
sign_vectors/oriented_matroids.py
sign_vectors/sign_vectors.py
sign_vectors/utility.py
sign_vectors-1.2.dist-info/licenses/LICENSE
sign_vectors-1.2.dist-info/METADATA
sign_vectors-1.2.dist-info/WHEEL
sign_vectors-1.2.dist-info/top_level.txt
sign_vectors-1.2.dist-info/RECORD
