Metadata-Version: 2.4
Name: sign_vectors
Version: 1.2
Summary: SageMath package for sign vectors, oriented matroids and chirotopes
Home-page: https://github.com/MarcusAichmayr/sign_vectors
Author: Marcus S. Aichmayr
Author-email: aichmayr@mathematik.uni-kassel.de
License: GPL-3.0-or-later
Keywords: sign vectors,oriented matroids,chirotopes
Classifier: Development Status :: 4 - Beta
Classifier: Programming Language :: Python :: 3
Classifier: Operating System :: OS Independent
Classifier: Intended Audience :: Science/Research
Classifier: Topic :: Scientific/Engineering :: Mathematics
License-File: LICENSE
Provides-Extra: passagemath
Requires-Dist: passagemath-symbolics; extra == "passagemath"
Requires-Dist: passagemath-flint; extra == "passagemath"
Requires-Dist: passagemath-graphs; extra == "passagemath"
Requires-Dist: passagemath-repl; extra == "passagemath"
Dynamic: author
Dynamic: author-email
Dynamic: classifier
Dynamic: description
Dynamic: description-content-type
Dynamic: home-page
Dynamic: keywords
Dynamic: license
Dynamic: license-file
Dynamic: provides-extra
Dynamic: summary
